taos_ws_py-0.6.5.dist-info/METADATA
taos_ws_py-0.6.5.dist-info/WHEEL
taosws/__init__.py
taosws/taosws.abi3.so
taos_ws_py-0.6.5.dist-info/RECORD
