Metadata-Version: 2.4
Name: taos-ws-py
Version: 0.6.5
